{
	"configurations" : 
	[
		{
			"directories" : 
			[
				{
					"build" : ".",
					"minimumCMakeVersion" : 
					{
						"string" : "3.6.0"
					},
					"projectIndex" : 0,
					"source" : ".",
					"targetIndexes" : 
					[
						0
					]
				}
			],
			"name" : "RelWithDebInfo",
			"projects" : 
			[
				{
					"directoryIndexes" : 
					[
						0
					],
					"name" : "hellovkjni",
					"targetIndexes" : 
					[
						0
					]
				}
			],
			"targets" : 
			[
				{
					"directoryIndex" : 0,
					"id" : "hellovkjni::@6890427a1f51a3e7e1df",
					"jsonFile" : "target-hellovkjni-RelWithDebInfo-5111dddc54a16421220e.json",
					"name" : "hellovkjni",
					"projectIndex" : 0
				}
			]
		}
	],
	"kind" : "codemodel",
	"paths" : 
	{
		"build" : "C:/Development/ndk-samples-main/hello-vulkan/app/.cxx/RelWithDebInfo/4a3q2s3e/x86",
		"source" : "C:/Development/ndk-samples-main/hello-vulkan/app/src/main/cpp"
	},
	"version" : 
	{
		"major" : 2,
		"minor" : 1
	}
}
